{"type":"Topology","bbox":[22.351957935904238,-5.684341886080802e-14,377.6480420640962,399.99999999999994],"transform":{"scale":[0.0035529963712456324,0.004000040000400004],"translate":[22.351957935904238,-5.684341886080802e-14]},"objects":{"counties":{"type":"GeometryCollection","geometries":[{"type":"Polygon","arcs":[[0,1,2,3,4]],"properties":{"STATEFP":"27","COUNTYFP":"023","COUNTYNS":"00659457","AFFGEOID":"0500000US27023","GEOID":"27023","NAME":"Chippewa","LSAD":"06","ALAND":1505064475,"AWATER":17233195}},{"type":"Polygon","arcs":[[5,6,7,8,9,10,11]],"properties":{"STATEFP":"27","COUNTYFP":"053","COUNTYNS":"00659472","AFFGEOID":"0500000US27053","GEOID":"27053","NAME":"Hennepin","LSAD":"06","ALAND":1433839320,"AWATER":137173629}},{"type":"Polygon","arcs":[[12,13,14,15]],"properties":{"STATEFP":"27","COUNTYFP":"077","COUNTYNS":"00659483","AFFGEOID":"0500000US27077","GEOID":"27077","NAME":"Lake of the Woods","LSAD":"06","ALAND":3361462398,"AWATER":1247519338}},{"type":"Polygon","arcs":[[16,17,18,19,20,21]],"properties":{"STATEFP":"27","COUNTYFP":"101","COUNTYNS":"00659496","AFFGEOID":"0500000US27101","GEOID":"27101","NAME":"Murray","LSAD":"06","ALAND":1825163785,"AWATER":38338284}},{"type":"Polygon","arcs":[[22,23,24,25,26,27,28,29,-3]],"properties":{"STATEFP":"27","COUNTYFP":"129","COUNTYNS":"00659510","AFFGEOID":"0500000US27129","GEOID":"27129","NAME":"Renville","LSAD":"06","ALAND":2545744678,"AWATER":10851893}},{"type":"Polygon","arcs":[[30,-11,31,32,33,34]],"properties":{"STATEFP":"27","COUNTYFP":"139","COUNTYNS":"00659514","AFFGEOID":"0500000US27139","GEOID":"27139","NAME":"Scott","LSAD":"06","ALAND":922693644,"AWATER":31374929}},{"type":"Polygon","arcs":[[35,36,37,38,39]],"properties":{"STATEFP":"27","COUNTYFP":"163","COUNTYNS":"00659526","AFFGEOID":"0500000US27163","GEOID":"27163","NAME":"Washington","LSAD":"06","ALAND":995558956,"AWATER":99517524}},{"type":"Polygon","arcs":[[40,41,42,43,44]],"properties":{"STATEFP":"27","COUNTYFP":"011","COUNTYNS":"00659451","AFFGEOID":"0500000US27011","GEOID":"27011","NAME":"Big Stone","LSAD":"06","ALAND":1292477791,"AWATER":75340289}},{"type":"Polygon","arcs":[[45,46,47,48,49,50,51]],"properties":{"STATEFP":"27","COUNTYFP":"013","COUNTYNS":"00659452","AFFGEOID":"0500000US27013","GEOID":"27013","NAME":"Blue Earth","LSAD":"06","ALAND":1936830865,"AWATER":46082217}},{"type":"Polygon","arcs":[[52,53,54,55,56]],"properties":{"STATEFP":"27","COUNTYFP":"027","COUNTYNS":"00659459","AFFGEOID":"0500000US27027","GEOID":"27027","NAME":"Clay","LSAD":"06","ALAND":2707039036,"AWATER":19306174}},{"type":"MultiPolygon","arcs":[[[57]],[[58,59]]],"properties":{"STATEFP":"27","COUNTYFP":"031","COUNTYNS":"00659461","AFFGEOID":"0500000US27031","GEOID":"27031","NAME":"Cook","LSAD":"06","ALAND":3761621396,"AWATER":4887941604}},{"type":"Polygon","arcs":[[-43,60,-5,61,62]],"properties":{"STATEFP":"27","COUNTYFP":"073","COUNTYNS":"00659482","AFFGEOID":"0500000US27073","GEOID":"27073","NAME":"Lac qui Parle","LSAD":"06","ALAND":1981394520,"AWATER":33643131}},{"type":"MultiPolygon","arcs":[[[63,-60,64,65]]],"properties":{"STATEFP":"27","COUNTYFP":"075","COUNTYNS":"00659484","AFFGEOID":"0500000US27075","GEOID":"27075","NAME":"Lake","LSAD":"06","ALAND":5463008925,"AWATER":2282651295}},{"type":"Polygon","arcs":[[66,67,68,69,70,71]],"properties":{"STATEFP":"27","COUNTYFP":"089","COUNTYNS":"00659489","AFFGEOID":"0500000US27089","GEOID":"27089","NAME":"Marshall","LSAD":"06","ALAND":4597384434,"AWATER":98019666}},{"type":"Polygon","arcs":[[72,73,74,75,76,77]],"properties":{"STATEFP":"27","COUNTYFP":"097","COUNTYNS":"00659494","AFFGEOID":"0500000US27097","GEOID":"27097","NAME":"Morrison","LSAD":"06","ALAND":2913973124,"AWATER":73283119}},{"type":"Polygon","arcs":[[-70,78,79,80,81,82]],"properties":{"STATEFP":"27","COUNTYFP":"113","COUNTYNS":"00659502","AFFGEOID":"0500000US27113","GEOID":"27113","NAME":"Pennington","LSAD":"06","ALAND":1596928760,"AWATER":4332057}},{"type":"Polygon","arcs":[[83,-29,84,85,-18,86]],"properties":{"STATEFP":"27","COUNTYFP":"127","COUNTYNS":"00659509","AFFGEOID":"0500000US27127","GEOID":"27127","NAME":"Redwood","LSAD":"06","ALAND":2275500535,"AWATER":8220933}},{"type":"Polygon","arcs":[[87,-6,88,89,90,91]],"properties":{"STATEFP":"27","COUNTYFP":"171","COUNTYNS":"00659530","AFFGEOID":"0500000US27171","GEOID":"27171","NAME":"Wright","LSAD":"06","ALAND":1712598664,"AWATER":137298052}},{"type":"Polygon","arcs":[[92,93,94,95,96,-73,97,98]],"properties":{"STATEFP":"27","COUNTYFP":"021","COUNTYNS":"00659456","AFFGEOID":"0500000US27021","GEOID":"27021","NAME":"Cass","LSAD":"06","ALAND":5235576788,"AWATER":1016652167}},{"type":"Polygon","arcs":[[-85,-28,99,-52,100,101]],"properties":{"STATEFP":"27","COUNTYFP":"015","COUNTYNS":"00659453","AFFGEOID":"0500000US27015","GEOID":"27015","NAME":"Brown","LSAD":"06","ALAND":1582659431,"AWATER":18584892}},{"type":"Polygon","arcs":[[102,103,104,105]],"properties":{"STATEFP":"27","COUNTYFP":"087","COUNTYNS":"00659488","AFFGEOID":"0500000US27087","GEOID":"27087","NAME":"Mahnomen","LSAD":"06","ALAND":1444886580,"AWATER":64851262}},{"type":"Polygon","arcs":[[106,107,108,109,110]],"properties":{"STATEFP":"27","COUNTYFP":"051","COUNTYNS":"00659471","AFFGEOID":"0500000US27051","GEOID":"27051","NAME":"Grant","LSAD":"06","ALAND":1418786606,"AWATER":71704359}},{"type":"Polygon","arcs":[[111,-66,112,113,114,115,116]],"properties":{"STATEFP":"27","COUNTYFP":"137","COUNTYNS":"00662850","AFFGEOID":"0500000US27137","GEOID":"27137","NAME":"St. Louis","LSAD":"06","ALAND":16181092598,"AWATER":1584976832}},{"type":"Polygon","arcs":[[-71,-83,117,-81,118,-103,119,120]],"properties":{"STATEFP":"27","COUNTYFP":"119","COUNTYNS":"00659505","AFFGEOID":"0500000US27119","GEOID":"27119","NAME":"Polk","LSAD":"06","ALAND":5105067510,"AWATER":69169913}},{"type":"Polygon","arcs":[[-56,121,-107,122,123]],"properties":{"STATEFP":"27","COUNTYFP":"167","COUNTYNS":"00659528","AFFGEOID":"0500000US27167","GEOID":"27167","NAME":"Wilkin","LSAD":"06","ALAND":1945079886,"AWATER":482554}},{"type":"Polygon","arcs":[[124,-67,125]],"properties":{"STATEFP":"27","COUNTYFP":"069","COUNTYNS":"00659480","AFFGEOID":"0500000US27069","GEOID":"27069","NAME":"Kittson","LSAD":"06","ALAND":2845894834,"AWATER":12411766}},{"type":"Polygon","arcs":[[-120,-106,126,-53,127]],"properties":{"STATEFP":"27","COUNTYFP":"107","COUNTYNS":"00659499","AFFGEOID":"0500000US27107","GEOID":"27107","NAME":"Norman","LSAD":"06","ALAND":2260512389,"AWATER":10208057}},{"type":"Polygon","arcs":[[-127,-105,128,129,130,131,-54]],"properties":{"STATEFP":"27","COUNTYFP":"005","COUNTYNS":"00659448","AFFGEOID":"0500000US27005","GEOID":"27005","NAME":"Becker","LSAD":"06","ALAND":3406166398,"AWATER":336840617}},{"type":"Polygon","arcs":[[-89,-12,-31,132,133]],"properties":{"STATEFP":"27","COUNTYFP":"019","COUNTYNS":"00659455","AFFGEOID":"0500000US27019","GEOID":"27019","NAME":"Carver","LSAD":"06","ALAND":917348283,"AWATER":56768380}},{"type":"Polygon","arcs":[[134,135,-129,-104,-119,-80]],"properties":{"STATEFP":"27","COUNTYFP":"029","COUNTYNS":"00659460","AFFGEOID":"0500000US27029","GEOID":"27029","NAME":"Clearwater","LSAD":"06","ALAND":2587409023,"AWATER":79744538}},{"type":"Polygon","arcs":[[-86,-102,136,137,138,-19]],"properties":{"STATEFP":"27","COUNTYFP":"033","COUNTYNS":"00659462","AFFGEOID":"0500000US27033","GEOID":"27033","NAME":"Cottonwood","LSAD":"06","ALAND":1657445964,"AWATER":22318968}},{"type":"Polygon","arcs":[[-49,139,140,141,142]],"properties":{"STATEFP":"27","COUNTYFP":"043","COUNTYNS":"00659467","AFFGEOID":"0500000US27043","GEOID":"27043","NAME":"Faribault","LSAD":"06","ALAND":1845301801,"AWATER":24422161}},{"type":"Polygon","arcs":[[143,-117,144,145,-14]],"properties":{"STATEFP":"27","COUNTYFP":"071","COUNTYNS":"00659481","AFFGEOID":"0500000US27071","GEOID":"27071","NAME":"Koochiching","LSAD":"06","ALAND":8039819178,"AWATER":129002560}},{"type":"Polygon","arcs":[[146,147,148,149]],"properties":{"STATEFP":"27","COUNTYFP":"081","COUNTYNS":"00659486","AFFGEOID":"0500000US27081","GEOID":"27081","NAME":"Lincoln","LSAD":"06","ALAND":1390177661,"AWATER":30255242}},{"type":"Polygon","arcs":[[150,-50,-143,151,152]],"properties":{"STATEFP":"27","COUNTYFP":"091","COUNTYNS":"00659490","AFFGEOID":"0500000US27091","GEOID":"27091","NAME":"Martin","LSAD":"06","ALAND":1844947511,"AWATER":44649915}},{"type":"Polygon","arcs":[[153,154,155,156,157,-75,158]],"properties":{"STATEFP":"27","COUNTYFP":"095","COUNTYNS":"00659493","AFFGEOID":"0500000US27095","GEOID":"27095","NAME":"Mille Lacs","LSAD":"06","ALAND":1482348668,"AWATER":282998978}},{"type":"Polygon","arcs":[[159,160,161,162,163,164]],"properties":{"STATEFP":"27","COUNTYFP":"109","COUNTYNS":"00659500","AFFGEOID":"0500000US27109","GEOID":"27109","NAME":"Olmsted","LSAD":"06","ALAND":1692581425,"AWATER":3505507}},{"type":"Polygon","arcs":[[-82,-118]],"properties":{"STATEFP":"27","COUNTYFP":"125","COUNTYNS":"00659508","AFFGEOID":"0500000US27125","GEOID":"27125","NAME":"Red Lake","LSAD":"06","ALAND":1119929328,"AWATER":227815}},{"type":"Polygon","arcs":[[165,-21,166,167]],"properties":{"STATEFP":"27","COUNTYFP":"133","COUNTYNS":"00659512","AFFGEOID":"0500000US27133","GEOID":"27133","NAME":"Rock","LSAD":"06","ALAND":1249560774,"AWATER":698231}},{"type":"Polygon","arcs":[[168,-98,-78,169,170,171]],"properties":{"STATEFP":"27","COUNTYFP":"153","COUNTYNS":"00659521","AFFGEOID":"0500000US27153","GEOID":"27153","NAME":"Todd","LSAD":"06","ALAND":2447451028,"AWATER":89444026}},{"type":"Polygon","arcs":[[172,173,-162,174]],"properties":{"STATEFP":"27","COUNTYFP":"157","COUNTYNS":"00659523","AFFGEOID":"0500000US27157","GEOID":"27157","NAME":"Wabasha","LSAD":"06","ALAND":1354359268,"AWATER":68954671}},{"type":"Polygon","arcs":[[-96,175,-115,176,177,178,-154,179]],"properties":{"STATEFP":"27","COUNTYFP":"001","COUNTYNS":"00663198","AFFGEOID":"0500000US27001","GEOID":"27001","NAME":"Aitkin","LSAD":"06","ALAND":4718271444,"AWATER":449535492}},{"type":"Polygon","arcs":[[180,-15,-146,181,-94,182,-135,-79,-69]],"properties":{"STATEFP":"27","COUNTYFP":"007","COUNTYNS":"00659449","AFFGEOID":"0500000US27007","GEOID":"27007","NAME":"Beltrami","LSAD":"06","ALAND":6487120495,"AWATER":1426321738}},{"type":"Polygon","arcs":[[183,184,185]],"properties":{"STATEFP":"27","COUNTYFP":"055","COUNTYNS":"00659473","AFFGEOID":"0500000US27055","GEOID":"27055","NAME":"Houston","LSAD":"06","ALAND":1429784922,"AWATER":43495762}},{"type":"Polygon","arcs":[[186,187,188,189,-156]],"properties":{"STATEFP":"27","COUNTYFP":"059","COUNTYNS":"00659475","AFFGEOID":"0500000US27059","GEOID":"27059","NAME":"Isanti","LSAD":"06","ALAND":1128567937,"AWATER":41166465}},{"type":"Polygon","arcs":[[-179,190,-187,-155]],"properties":{"STATEFP":"27","COUNTYFP":"065","COUNTYNS":"00659478","AFFGEOID":"0500000US27065","GEOID":"27065","NAME":"Kanabec","LSAD":"06","ALAND":1350910899,"AWATER":31322650}},{"type":"Polygon","arcs":[[191,-87,-17,192,-148]],"properties":{"STATEFP":"27","COUNTYFP":"083","COUNTYNS":"00659487","AFFGEOID":"0500000US27083","GEOID":"27083","NAME":"Lyon","LSAD":"06","ALAND":1850315135,"AWATER":18794796}},{"type":"Polygon","arcs":[[-90,-134,193,-25,194]],"properties":{"STATEFP":"27","COUNTYFP":"085","COUNTYNS":"00659491","AFFGEOID":"0500000US27085","GEOID":"27085","NAME":"McLeod","LSAD":"06","ALAND":1272940264,"AWATER":36370228}},{"type":"Polygon","arcs":[[195,-91,-195,-24,196]],"properties":{"STATEFP":"27","COUNTYFP":"093","COUNTYNS":"00659492","AFFGEOID":"0500000US27093","GEOID":"27093","NAME":"Meeker","LSAD":"06","ALAND":1575108557,"AWATER":94852453}},{"type":"Polygon","arcs":[[197,198,-165,199,200,201]],"properties":{"STATEFP":"27","COUNTYFP":"099","COUNTYNS":"00659495","AFFGEOID":"0500000US27099","GEOID":"27099","NAME":"Mower","LSAD":"06","ALAND":1842332253,"AWATER":617233}},{"type":"Polygon","arcs":[[-149,-193,-22,-166,202]],"properties":{"STATEFP":"27","COUNTYFP":"117","COUNTYNS":"00659504","AFFGEOID":"0500000US27117","GEOID":"27117","NAME":"Pipestone","LSAD":"06","ALAND":1204488112,"AWATER":2348855}},{"type":"Polygon","arcs":[[203,204,205,206,207]],"properties":{"STATEFP":"27","COUNTYFP":"121","COUNTYNS":"00659506","AFFGEOID":"0500000US27121","GEOID":"27121","NAME":"Pope","LSAD":"06","ALAND":1734134611,"AWATER":123231111}},{"type":"Polygon","arcs":[[-36,208,-9,209]],"properties":{"STATEFP":"27","COUNTYFP":"123","COUNTYNS":"00659507","AFFGEOID":"0500000US27123","GEOID":"27123","NAME":"Ramsey","LSAD":"06","ALAND":394086546,"AWATER":46423262}},{"type":"Polygon","arcs":[[-33,210,211,212,213,214,215]],"properties":{"STATEFP":"27","COUNTYFP":"131","COUNTYNS":"00659511","AFFGEOID":"0500000US27131","GEOID":"27131","NAME":"Rice","LSAD":"06","ALAND":1284224027,"AWATER":52057387}},{"type":"Polygon","arcs":[[216,-16,-181,-68,-125]],"properties":{"STATEFP":"27","COUNTYFP":"135","COUNTYNS":"00659513","AFFGEOID":"0500000US27135","GEOID":"27135","NAME":"Roseau","LSAD":"06","ALAND":4329471930,"AWATER":16913419}},{"type":"Polygon","arcs":[[217,-157,-190,218,-7,-88,219]],"properties":{"STATEFP":"27","COUNTYFP":"141","COUNTYNS":"00659515","AFFGEOID":"0500000US27141","GEOID":"27141","NAME":"Sherburne","LSAD":"06","ALAND":1121229505,"AWATER":46967228}},{"type":"Polygon","arcs":[[-214,220,-198,221,222]],"properties":{"STATEFP":"27","COUNTYFP":"147","COUNTYNS":"00659518","AFFGEOID":"0500000US27147","GEOID":"27147","NAME":"Steele","LSAD":"06","ALAND":1112775698,"AWATER":6976791}},{"type":"Polygon","arcs":[[223,-207,224,-1,-61,-42]],"properties":{"STATEFP":"27","COUNTYFP":"151","COUNTYNS":"00659520","AFFGEOID":"0500000US27151","GEOID":"27151","NAME":"Swift","LSAD":"06","ALAND":1921870987,"AWATER":26208987}},{"type":"Polygon","arcs":[[-123,-111,225,-45,226]],"properties":{"STATEFP":"27","COUNTYFP":"155","COUNTYNS":"00659522","AFFGEOID":"0500000US27155","GEOID":"27155","NAME":"Traverse","LSAD":"06","ALAND":1486320975,"AWATER":31025234}},{"type":"Polygon","arcs":[[-131,227,-99,-169,228]],"properties":{"STATEFP":"27","COUNTYFP":"159","COUNTYNS":"00659524","AFFGEOID":"0500000US27159","GEOID":"27159","NAME":"Wadena","LSAD":"06","ALAND":1388921383,"AWATER":18038938}},{"type":"Polygon","arcs":[[229,-184,230,-163,-174]],"properties":{"STATEFP":"27","COUNTYFP":"169","COUNTYNS":"00659529","AFFGEOID":"0500000US27169","GEOID":"27169","NAME":"Winona","LSAD":"06","ALAND":1621558336,"AWATER":40131783}},{"type":"Polygon","arcs":[[-114,231,232,-177]],"properties":{"STATEFP":"27","COUNTYFP":"017","COUNTYNS":"00659454","AFFGEOID":"0500000US27017","GEOID":"27017","NAME":"Carlton","LSAD":"06","ALAND":2230821123,"AWATER":36133708}},{"type":"Polygon","arcs":[[-97,-180,-159,-74]],"properties":{"STATEFP":"27","COUNTYFP":"035","COUNTYNS":"00659463","AFFGEOID":"0500000US27035","GEOID":"27035","NAME":"Crow Wing","LSAD":"06","ALAND":2585785629,"AWATER":409661410}},{"type":"Polygon","arcs":[[233,-171,234,-204,-109]],"properties":{"STATEFP":"27","COUNTYFP":"041","COUNTYNS":"00659466","AFFGEOID":"0500000US27041","GEOID":"27041","NAME":"Douglas","LSAD":"06","ALAND":1649200283,"AWATER":215604217}},{"type":"Polygon","arcs":[[-164,-231,-186,235,-200]],"properties":{"STATEFP":"27","COUNTYFP":"045","COUNTYNS":"00659468","AFFGEOID":"0500000US27045","GEOID":"27045","NAME":"Fillmore","LSAD":"06","ALAND":2230746823,"AWATER":2055507}},{"type":"Polygon","arcs":[[236,237,-175,-161,238,-212]],"properties":{"STATEFP":"27","COUNTYFP":"049","COUNTYNS":"00659470","AFFGEOID":"0500000US27049","GEOID":"27049","NAME":"Goodhue","LSAD":"06","ALAND":1960231247,"AWATER":61007223}},{"type":"Polygon","arcs":[[239,-222,-202,240,-141]],"properties":{"STATEFP":"27","COUNTYFP":"047","COUNTYNS":"00659469","AFFGEOID":"0500000US27047","GEOID":"27047","NAME":"Freeborn","LSAD":"06","ALAND":1831351973,"AWATER":39709692}},{"type":"Polygon","arcs":[[-213,-239,-160,-199,-221]],"properties":{"STATEFP":"27","COUNTYFP":"039","COUNTYNS":"00659465","AFFGEOID":"0500000US27039","GEOID":"27039","NAME":"Dodge","LSAD":"06","ALAND":1137724830,"AWATER":800245}},{"type":"Polygon","arcs":[[-138,241,-153,242,243]],"properties":{"STATEFP":"27","COUNTYFP":"063","COUNTYNS":"00659477","AFFGEOID":"0500000US27063","GEOID":"27063","NAME":"Jackson","LSAD":"06","ALAND":1820689421,"AWATER":42120425}},{"type":"Polygon","arcs":[[-178,-233,244,245,-191]],"properties":{"STATEFP":"27","COUNTYFP":"115","COUNTYNS":"00659503","AFFGEOID":"0500000US27115","GEOID":"27115","NAME":"Pine","LSAD":"06","ALAND":3655221004,"AWATER":60262765}},{"type":"Polygon","arcs":[[-194,-133,-35,246,247,-26]],"properties":{"STATEFP":"27","COUNTYFP":"143","COUNTYNS":"00659516","AFFGEOID":"0500000US27143","GEOID":"27143","NAME":"Sibley","LSAD":"06","ALAND":1524941287,"AWATER":30470667}},{"type":"Polygon","arcs":[[-158,-218,248,-76]],"properties":{"STATEFP":"27","COUNTYFP":"009","COUNTYNS":"00659450","AFFGEOID":"0500000US27009","GEOID":"27009","NAME":"Benton","LSAD":"06","ALAND":1057483363,"AWATER":12286992}},{"type":"Polygon","arcs":[[-183,-93,-228,-130,-136]],"properties":{"STATEFP":"27","COUNTYFP":"057","COUNTYNS":"00659474","AFFGEOID":"0500000US27057","GEOID":"27057","NAME":"Hubbard","LSAD":"06","ALAND":2398071535,"AWATER":190599026}},{"type":"Polygon","arcs":[[-20,-139,-244,249,-167]],"properties":{"STATEFP":"27","COUNTYFP":"105","COUNTYNS":"00659498","AFFGEOID":"0500000US27105","GEOID":"27105","NAME":"Nobles","LSAD":"06","ALAND":1852077339,"AWATER":19323570}},{"type":"Polygon","arcs":[[-110,-208,-224,-41,-226]],"properties":{"STATEFP":"27","COUNTYFP":"149","COUNTYNS":"00659519","AFFGEOID":"0500000US27149","GEOID":"27149","NAME":"Stevens","LSAD":"06","ALAND":1459747661,"AWATER":30319494}},{"type":"Polygon","arcs":[[-246,250,-38,251,-188]],"properties":{"STATEFP":"27","COUNTYFP":"025","COUNTYNS":"00659458","AFFGEOID":"0500000US27025","GEOID":"27025","NAME":"Chisago","LSAD":"06","ALAND":1074617226,"AWATER":71151170}},{"type":"Polygon","arcs":[[-247,-34,-216,252,-47,253]],"properties":{"STATEFP":"27","COUNTYFP":"079","COUNTYNS":"00659485","AFFGEOID":"0500000US27079","GEOID":"27079","NAME":"Le Sueur","LSAD":"06","ALAND":1162055133,"AWATER":65130232}},{"type":"Polygon","arcs":[[-55,-132,-229,-172,-234,-108,-122]],"properties":{"STATEFP":"27","COUNTYFP":"111","COUNTYNS":"00659501","AFFGEOID":"0500000US27111","GEOID":"27111","NAME":"Otter Tail","LSAD":"06","ALAND":5107436184,"AWATER":654101087}},{"type":"Polygon","arcs":[[-101,-51,-151,-242,-137]],"properties":{"STATEFP":"27","COUNTYFP":"165","COUNTYNS":"00659527","AFFGEOID":"0500000US27165","GEOID":"27165","NAME":"Watonwan","LSAD":"06","ALAND":1126526382,"AWATER":12370135}},{"type":"Polygon","arcs":[[-10,-209,-40,254,-237,-211,-32]],"properties":{"STATEFP":"27","COUNTYFP":"037","COUNTYNS":"00659464","AFFGEOID":"0500000US27037","GEOID":"27037","NAME":"Dakota","LSAD":"06","ALAND":1456715603,"AWATER":63149548}},{"type":"Polygon","arcs":[[-189,-252,-37,-210,-8,-219]],"properties":{"STATEFP":"27","COUNTYFP":"003","COUNTYNS":"00659447","AFFGEOID":"0500000US27003","GEOID":"27003","NAME":"Anoka","LSAD":"06","ALAND":1095486322,"AWATER":59843479}},{"type":"Polygon","arcs":[[-145,-116,-176,-95,-182]],"properties":{"STATEFP":"27","COUNTYFP":"061","COUNTYNS":"00659476","AFFGEOID":"0500000US27061","GEOID":"27061","NAME":"Itasca","LSAD":"06","ALAND":6907775594,"AWATER":675388758}},{"type":"Polygon","arcs":[[-253,-215,-223,-240,-140,-48]],"properties":{"STATEFP":"27","COUNTYFP":"161","COUNTYNS":"00659525","AFFGEOID":"0500000US27161","GEOID":"27161","NAME":"Waseca","LSAD":"06","ALAND":1096505111,"AWATER":24893716}},{"type":"Polygon","arcs":[[-27,-248,-254,-46,-100]],"properties":{"STATEFP":"27","COUNTYFP":"103","COUNTYNS":"00659497","AFFGEOID":"0500000US27103","GEOID":"27103","NAME":"Nicollet","LSAD":"06","ALAND":1161921138,"AWATER":47467472}},{"type":"Polygon","arcs":[[-62,-4,-30,-84,-192,-147,255]],"properties":{"STATEFP":"27","COUNTYFP":"173","COUNTYNS":"00659531","AFFGEOID":"0500000US27173","GEOID":"27173","NAME":"Yellow Medicine","LSAD":"06","ALAND":1966062971,"AWATER":10687958}},{"type":"Polygon","arcs":[[-206,256,-197,-23,-2,-225]],"properties":{"STATEFP":"27","COUNTYFP":"067","COUNTYNS":"00659479","AFFGEOID":"0500000US27067","GEOID":"27067","NAME":"Kandiyohi","LSAD":"06","ALAND":2064978211,"AWATER":168506888}},{"type":"Polygon","arcs":[[-235,-170,-77,-249,-220,-92,-196,-257,-205]],"properties":{"STATEFP":"27","COUNTYFP":"145","COUNTYNS":"00659517","AFFGEOID":"0500000US27145","GEOID":"27145","NAME":"Stearns","LSAD":"06","ALAND":3477880457,"AWATER":122121594}}]}},"arcs":[[[15308,71756],[1020,7],[2430,-1],[889,3],[1379,-4],[1654,-12],[1651,-27],[1661,-5]],[[25992,71717],[8,1484],[-6,1487],[11,1485]],[[26005,76173],[-3181,29],[-6,618],[21,1742]],[[22839,78562],[-117,-4],[23,-196],[-78,-95],[-130,-53],[-43,108],[-103,1],[7,-73],[-140,24],[-71,-86],[104,-11],[-35,-135],[169,-6],[198,-60],[-76,-129],[-211,-126],[-349,-27],[127,-136],[-118,-135],[-216,-64],[-93,-98],[16,-76],[-106,-118],[-45,25],[-321,-72],[52,-80],[-60,-53],[-193,5],[8,-152],[-86,-134],[-80,-23],[-84,-154],[-113,63],[-178,-179],[82,-65],[-99,-9],[-235,-128],[8,-129],[-93,-75],[-112,108],[-302,-21],[-189,-111],[64,-22],[-8,-172],[-237,-249]],[[19376,75440],[-136,-148],[-152,-19],[21,73],[-178,-108],[-9,75],[-271,-99],[-5,50],[-189,-49],[-95,-209],[-95,14],[-65,-72],[-20,-373],[-194,-202],[-299,-150],[-121,-288],[-69,40],[-119,-101],[22,-89],[-172,-55],[-1159,-1042],[-170,-226],[-82,-13],[-60,-183],[-123,-24],[-33,-85],[-141,-129],[-154,-272]],[[46067,74413],[-28,-1403],[25,-186],[81,-33],[-50,-141],[185,32],[121,-34],[136,-157],[-13,-127],[114,-292],[236,-294],[23,-86],[149,-123],[70,-114],[241,-82],[67,18],[179,-94],[120,-122],[-5,-146],[-175,-139],[-108,-186],[22,-68],[133,-38],[94,-168],[72,0],[53,107],[83,-1],[-13,-112],[172,-40],[26,57],[88,-83],[32,81],[113,-24],[12,-154],[41,60],[261,-69],[116,-148],[180,1],[66,-102],[117,32],[77,137],[111,-272],[69,-30],[-97,-112]],[[49263,69758],[128,13]],[[49391,69771],[164,83],[48,106],[159,143],[205,-9],[166,91],[217,63],[122,-30],[113,63],[183,268],[226,111],[278,209],[226,58],[179,248],[215,117],[100,92],[162,59],[204,282],[38,204],[230,192],[3,396],[-72,372],[68,253],[-31,140],[765,-24]],[[53359,73258],[255,-8],[23,485],[28,923],[105,197],[23,560],[122,78],[20,137],[178,31],[-15,93]],[[54098,75754],[-59,53],[60,87],[-279,258],[39,91],[-180,352],[-131,25],[31,106],[-114,58],[-320,308],[-390,97],[-58,75],[-260,139],[-337,64]],[[52100,77467],[-130,79],[-146,-77],[-71,100],[-119,-55],[-227,62],[-72,-205],[-145,18],[-134,-129],[-187,-33],[-270,-97],[-64,131],[-185,39],[-73,-54],[-169,43],[-124,-50],[-109,54],[-49,-80],[-90,76],[-235,15]],[[49501,77304],[-18,-382],[-30,-1107],[-502,21],[-1436,24],[-577,26],[-827,14],[-34,-988],[12,-103],[-22,-396]],[[24475,6500],[2118,-17],[-26,-3129],[-34,-3354],[343,248],[865,266],[115,1],[442,-60],[321,-213],[186,17],[213,-43],[68,25],[547,305],[394,282],[309,148],[220,0],[263,48],[-99,206],[-13,243],[378,1343],[-6,276],[334,1294],[298,357],[424,1667],[471,1948],[5,194],[-105,60],[30,94],[-33,168],[98,222],[-206,143],[-28,127],[123,253],[-10,159],[25,296],[95,120],[184,93],[270,224],[141,244],[286,62],[228,149],[154,174],[272,36],[161,-13],[133,66],[91,159],[382,34],[119,38],[451,35],[156,50],[174,-44],[106,-104]],[[35908,11397],[51,1845],[2,859],[14,783],[26,748],[7,537],[25,855]],[[36033,17024],[-5036,73],[-5034,61],[-21,-969],[5,-484],[-24,-1483],[-1677,7]],[[24246,14229],[-25,-2914],[2283,-14],[955,-10],[-25,-1709],[-33,-1788],[-282,235],[-33,54],[-277,151],[-302,50],[-468,113],[-472,71],[-246,-49],[-425,-221],[-168,-107],[59,-69],[-187,-167],[-153,-288],[-3,-80],[96,-98],[135,-2],[-15,-60],[-152,-47],[-27,-188],[-74,-104],[-18,-206],[113,-238],[-27,-44]],[[14930,88082],[4299,0],[645,5],[1504,-1]],[[21378,88086],[1043,-2],[754,-12]],[[23175,88072],[13,1490],[19,2975],[-1,752],[9,736]],[[23215,94025],[-1517,7],[-1252,-1],[-1507,5],[-3856,-12]],[[15083,94024],[-169,0]],[[14914,94024],[9,-1481],[-5,-1490],[12,-2971]],[[26005,76173],[980,-7],[2072,-23],[1886,-31],[1717,-15]],[[32660,76097],[1665,-16],[1806,-32]],[[36131,76049],[63,-1],[49,2991]],[[36243,79039],[-1788,32],[28,1492],[23,1486],[68,0],[26,1474]],[[34600,83523],[-1631,15],[-507,0]],[[32462,83538],[-130,8],[-45,-78],[-230,-176],[-17,-173],[-85,41],[-88,-108],[-306,-117],[-114,42],[9,-92],[-167,-44]],[[31289,82841],[-109,-20],[2,-105],[-95,-191],[-164,60],[3,-86],[-85,-39],[-52,60],[-166,27],[-226,-149],[-102,10],[-116,-90],[-306,-70],[-7,-111],[-85,88],[-7,-95],[-107,18],[-65,-109],[-140,-23],[-44,78],[-181,8],[-1,-150],[-130,85],[-105,-178],[-232,-18],[-132,-77],[3,-88],[-232,-101],[-86,83],[-207,-45],[-98,-266],[-145,-31],[-42,-94],[-201,-26],[-21,-91],[-170,-96],[-59,-133],[-218,-107],[-102,45],[-167,-91],[-156,-191],[-275,-164],[-287,-253],[-78,-114],[-163,97],[-166,41],[-295,-36],[-167,-115],[-136,-136],[19,-193],[-45,-71],[-175,-2],[-118,-51],[-255,-20],[-81,-41]],[[24514,79474],[-300,-120],[34,-93],[-157,1],[-140,-135],[57,-82],[-268,-183],[-333,-150],[-230,47],[-77,-135],[-65,-5],[-120,-120],[-76,63]],[[46211,80178],[170,89],[-62,-144],[302,-54],[129,-177],[170,-21],[-83,-92],[140,-94],[170,-25],[267,-323],[134,-127],[109,-7],[58,94],[75,-88],[125,36],[68,-81],[237,-171],[-118,-150],[21,-134],[-101,8],[40,-115],[-39,-133],[99,-117],[30,-148],[100,75],[75,-93],[-185,-100],[82,-107],[199,-54],[89,-119],[-70,-110],[237,-1],[11,-180],[332,-119],[118,65],[82,-53],[-4,-102],[283,-2]],[[52100,77467],[21,260],[36,995],[139,-4],[40,1485],[552,-16],[43,1482],[-41,1]],[[52890,81670],[-3312,86]],[[49578,81756],[-1673,33],[-1110,35],[-2482,52]],[[44313,81876],[46,-136],[87,-18],[15,112],[106,-14],[-3,-103],[-119,-53],[31,-114],[87,-63],[-125,-62],[70,-89],[28,-179],[-65,-72],[102,-129],[69,27],[99,-91],[-12,-93],[124,54],[113,-67],[83,-188],[-51,-67],[125,-14],[164,53],[248,-185],[32,-69],[215,-37],[123,105],[224,-162],[11,119],[133,-59],[-62,-104]],[[56247,75655],[486,-15],[-15,-317],[-100,-2669],[-33,-985],[-485,9]],[[56100,71678],[-42,-1484],[-48,-1467]],[[56010,68727],[1677,-36],[1077,-33],[940,-20]],[[59704,68638],[-174,88],[-18,208],[113,155],[19,134],[-108,209],[50,324],[86,200],[-27,102],[-129,138],[-26,332],[202,191],[-55,151],[10,227],[108,231],[61,255],[88,110],[-68,142],[-125,92],[-256,247],[-231,169],[-144,247],[16,136],[72,114],[255,185],[199,175],[33,139],[-105,330],[38,224],[5,274],[123,119],[89,155],[66,313],[-102,506],[-179,116],[-19,147],[157,284],[-58,237],[65,358],[-7,105],[-79,120],[-1,113],[-100,154],[-25,248],[-72,179],[-150,182],[-62,156],[-25,290],[77,94]],[[59291,78043],[-310,-66],[-146,53],[-262,2],[-249,-330],[-139,-110],[-418,2],[-167,-99],[-91,-3],[-101,96],[-325,105],[-305,-81],[-268,69],[-138,-62],[-83,-189],[73,-273],[139,-213],[-111,-370],[34,-263],[-12,-167],[-113,-386],[-52,-103]],[[12406,64363],[155,-1],[3,1236],[-10,1712],[845,13],[829,1]],[[14228,67324],[-18,349],[9,1245],[-9,1343],[194,0],[0,1077]],[[14404,71338],[-54,-112],[-412,-172],[-155,44],[-308,-36],[-472,-246],[-50,-104],[-172,-129],[-88,45],[-274,-16],[-102,-77],[-64,36],[-185,-39],[-78,-184],[-86,-74],[74,-139],[-250,-52],[-155,42],[14,-75],[-207,28],[-136,-99],[-164,9],[-105,-50],[-147,11],[-119,-54],[-398,71],[-157,-150],[-163,-70],[-300,6]],[[9691,69752],[1,-498],[-118,-270],[-232,-440],[-130,-298],[-173,-144],[-266,-174],[-325,-94],[-442,-194],[-299,-188],[-223,-85],[-406,-37],[-193,18],[-245,-27],[-162,-117],[-126,-153],[-296,-432],[-95,-95],[-185,-542],[-261,-559],[-210,-250],[-170,-252],[-108,-81],[-445,-527]],[[4582,64313],[2676,25],[1682,14],[1116,3],[1683,12],[667,-4]],[[38111,86749],[91,11],[97,114],[32,-80],[257,78],[121,120],[149,27],[-27,79],[270,9],[41,151],[85,-101],[268,248],[4,-98],[75,117],[137,-3],[125,94],[-58,58],[128,11],[47,72],[72,-48],[197,-23],[-37,139],[102,71],[215,-27],[115,74],[532,100],[127,-37],[120,117],[124,42],[0,75],[152,-23],[61,148],[159,-4],[-80,48],[167,43],[1,49],[254,92],[168,-74],[87,146],[105,-2],[50,-143],[143,-55],[305,-12],[103,-62],[-33,-238],[-201,-22],[56,-123],[98,31],[-46,-150],[-137,-33],[97,-62],[-68,-103],[-92,-24],[14,-172],[140,87],[4,-160],[-65,-170],[89,-59]],[[43051,87092],[1191,-28],[681,-4],[1469,-32],[20,745]],[[46412,87773],[63,2537],[98,3412]],[[46573,93722],[-2785,51],[-2188,44],[-1634,28]],[[39966,93845],[-1679,25]],[[38287,93870],[-61,-2973],[-24,-1486]],[[38202,89411],[-33,-1491],[-37,-124],[-21,-1047]],[[4788,37718],[1964,-1],[1653,8],[1531,15],[1641,0],[1674,7]],[[13251,37747],[8,2948],[256,0],[-4,1094],[-41,1835],[29,1477]],[[13499,45101],[28,1480],[-1438,-4]],[[12089,46577],[-3513,-9],[-3151,-17]],[[5425,46551],[-143,-19],[133,-149],[-108,-110],[46,-41],[-109,-86],[-9,-111],[103,-217],[-94,-82],[145,-5],[53,-109],[-78,-90],[72,-68],[-78,-147],[94,-50],[-70,-68],[85,-128],[-108,-6],[150,-92],[-13,-318],[-79,-174],[55,-76],[-62,-166],[125,34],[28,-56],[-161,-44],[-21,-70],[83,-64],[-171,12],[125,-121],[-90,-66],[-26,-343],[-80,-48],[62,-184],[86,-93],[148,37],[-168,-147],[105,23],[-25,-136],[155,38],[-82,-116],[103,-72],[-135,-35],[92,-89],[-88,-76],[104,-206],[-67,-94],[185,-72],[-96,-89],[69,-52],[-92,-63],[78,-78],[4,-110],[63,29],[44,-220],[118,59],[-128,-149],[78,-125],[-56,-67],[-177,64],[-141,99],[-78,-60],[24,-156],[-33,-155],[-158,-13],[81,-63],[-64,-123],[113,-118],[-74,-49],[-121,74],[-175,-119],[45,-111],[-81,-172],[69,-260],[-90,15],[-97,-90],[10,-167],[111,-104],[151,-34],[-152,-132],[135,-13],[48,-75],[-133,9],[70,-139],[-121,-17],[122,-80],[-93,-64],[51,-94],[-66,-265],[124,-32],[-47,-79],[64,-77],[-129,-45],[107,-31],[-49,-134],[58,-155],[-158,-201],[113,-126],[-115,-6],[39,-105],[-106,-156],[34,-94],[-102,-15]],[[98753,21456],[137,-196],[270,-44],[76,116],[-400,253],[-83,-129]],[[79915,18703],[341,-255],[335,-300],[657,-208],[130,-18],[98,-118],[266,-156],[142,129],[103,-12],[248,-118],[110,78],[117,855],[-15,198],[51,52],[111,-79],[26,-113],[49,85],[176,21],[60,244],[57,62],[259,-56],[-41,274],[-200,117],[24,67],[170,-7],[-95,98],[175,90],[223,426],[137,117],[127,-68],[486,-48],[216,-87],[578,-79],[181,-150],[451,-120],[112,-111],[85,45],[213,-24],[50,75],[-169,180],[36,96],[143,80],[509,-83],[388,-15],[239,-177],[207,54],[182,96],[356,-125],[91,-6],[225,105],[161,115],[85,-66],[271,-7],[104,-41],[102,-110],[312,-62],[217,92],[185,-83],[269,3],[370,-120],[173,23],[291,-44],[151,-85],[163,37],[260,-63],[145,7],[220,114],[317,-23],[449,115],[117,73],[336,99],[131,289],[84,-25],[150,175],[62,141],[-21,232],[56,116],[249,80],[88,136],[214,51],[12,-87],[209,-8],[107,228],[406,218],[340,8],[35,-68],[280,-64],[37,-149],[158,9],[119,-258],[157,-45],[37,57],[163,-85],[160,-12],[147,-80],[236,-26],[85,52],[114,-39],[41,49],[198,29],[3,104],[199,57],[156,-87],[194,-23],[121,54],[98,-41],[56,87],[207,-18],[-6,-73],[247,-43],[103,-103],[33,169],[290,74],[70,85],[456,-115],[234,-1],[194,-56],[-13,-38],[206,-28],[21,63],[-211,37],[-428,155],[-144,8],[-162,135],[-175,88],[-322,42],[-85,-79],[114,-71],[-150,-122],[-265,171],[-135,144],[30,116],[121,205],[11,105],[-159,-97],[-91,-116],[-237,42],[-137,126],[-23,86],[111,55],[16,86],[-209,74],[-186,123],[-5,49],[-210,119],[-66,132],[-255,177],[-3,64],[-209,50],[-250,197],[-80,17],[-353,202],[-131,-5],[-197,125],[-228,9],[-232,182],[-79,-58],[-198,108],[-150,12],[-88,78],[51,114],[-78,74],[-229,121],[-153,13],[-121,169],[-371,114],[-264,136],[-230,18],[-202,105],[-176,26],[-95,151],[-171,15],[-301,144],[-62,-15],[-348,39],[-152,38],[-226,121],[-108,169],[-173,37],[-160,-24],[-200,26],[-342,104],[-98,67],[-515,219],[-123,-2],[-205,109],[19,96],[-258,9],[-535,103],[-88,67],[-303,54],[-208,70],[-25,107],[-96,50],[-294,67],[-347,148],[-497,177],[-170,226],[-427,183],[-160,103],[-406,210],[-98,75],[-421,248],[-193,58],[-362,215],[-171,77],[-425,313],[-181,85],[-147,170],[-574,422],[-157,140],[-188,99],[-354,304],[-481,461],[-267,174],[-382,346],[-510,425]],[[80748,30920],[-134,-2317],[-97,-1923],[-160,-2911],[-75,-2],[-151,-2970],[-90,5],[-126,-1946],[0,-153]],[[14404,71338],[256,186],[121,-3],[300,162],[72,-34],[155,107]],[[19376,75440],[-6,761],[-1495,-2],[-18,1476],[-1106,6],[-2214,5],[-1661,-16],[-1673,4],[-1535,-15]],[[9668,77659],[3,-2683],[5,-251],[18,-3951],[-3,-1022]],[[70019,18885],[84,3],[41,98],[97,-69],[213,-11],[103,-93],[100,114],[92,-8],[-10,-90],[358,76],[61,86],[-19,109],[-110,127],[-32,163],[194,-42],[54,30],[12,187],[-38,120],[143,181],[-14,167],[-98,153],[-43,142],[111,15],[135,-53],[124,-102],[-53,178],[143,70],[120,-24],[179,-105],[0,78],[184,206],[317,-97],[340,-19],[165,-80],[213,-39],[86,86],[-208,172],[-50,460],[39,150],[-26,145],[113,81],[311,-174],[683,-279],[300,9],[194,-43],[174,276],[112,54],[199,-92],[291,-72],[250,-220],[76,38],[317,-120],[50,59],[150,-57],[445,-42],[180,-85],[123,-9],[205,-100],[185,-208],[258,-131],[288,-384],[96,41],[333,-324],[228,-157],[-73,-83],[290,-118],[62,-98],[284,-132],[116,-135],[221,-18],[102,-108],[326,-35]],[[80748,30920],[-122,120],[-163,37],[-171,227],[-59,12],[-77,163],[-208,200],[-96,136],[-135,55],[-274,219],[-35,104],[-130,102],[-209,236],[-208,274],[-54,197],[-65,19],[21,120],[-138,32],[-134,154],[-91,204],[-73,-8],[-116,190],[-121,43],[-93,184],[-25,174],[-274,132],[-93,184],[-129,15],[-8,131],[-160,64],[-298,283],[-18,97],[-307,293],[-46,188],[-98,9],[2,74],[-188,125],[-67,126],[-139,19],[-64,92],[-97,-4],[-16,99],[-114,67],[-335,413],[-111,82],[10,65],[-150,160],[-186,126],[-219,37],[-116,75],[-169,247],[-239,54],[-133,146],[-100,-12],[-210,85],[-125,196],[-128,282],[-110,-20],[-339,291],[-154,208],[75,31],[12,106],[-125,33],[-63,-62],[-111,55],[-3,192],[-206,-25],[-105,188],[-167,-8],[-94,38],[-407,397],[-242,265],[-130,179],[-133,91],[-24,156],[-182,67]],[[71139,40246],[-87,-1590],[-29,-766],[-31,-551],[32,-2],[-24,-228],[-199,-4193],[16,-1],[-31,-748],[-80,-2203],[-44,-548],[-24,-119],[-138,-1488],[-78,-760],[-89,-1402],[-25,-496],[-25,-1354],[-19,-119],[-66,-978],[-88,-1503],[-91,-2312]],[[871,14111],[1560,10],[1670,33],[3645,17],[1769,15],[1310,-9]],[[10825,14177],[139,4],[1810,-11],[1714,27],[1400,4],[568,17],[1118,16],[316,16],[793,-4],[842,15],[1386,7]],[[20911,14268],[16,115],[6,724],[-18,1595],[14,493],[113,-1],[8,3251]],[[21050,20445],[-1662,4],[-1398,18],[-1949,9],[-1638,-3],[-274,-19],[-567,-14],[-126,29],[-727,-14],[-271,-37],[-1109,7],[-283,-14],[-1136,10],[-573,-1]],[[9337,20420],[-279,4],[-2802,-10],[-1952,-10],[-3302,-33]],[[1002,20371],[129,-47],[-39,-112],[-132,-15],[185,-229],[-67,-94],[148,-88],[-125,-109],[105,-47],[85,156],[67,-92],[-68,-67],[-203,-82],[-119,67],[3,-85],[162,-63],[152,63],[12,-85],[-234,-50],[-21,-65],[110,-31],[2,-67],[-142,-21],[31,-68],[251,-63],[-67,-129],[82,-100],[-254,-40],[47,-89],[193,12],[0,-96],[115,-58],[-69,-176],[-65,-31],[-109,80],[-31,-65],[128,-133],[116,79],[79,-59],[-174,-117],[60,-89],[-149,14],[-54,-51],[55,-107],[224,-61],[-13,-65],[-208,-35],[103,-175],[-21,-74],[-154,-28],[44,-137],[-96,-37],[-148,-158],[10,-105],[200,-5],[-62,-189],[-165,-72],[-61,-153],[180,-32],[217,-163],[-1,-50],[-151,-145],[-57,80],[-89,-72],[187,-68],[183,94],[-8,-122],[-202,-74],[-32,-84],[175,26],[89,-41],[-23,-160],[-102,-5],[-85,79],[-121,-45],[197,-128],[78,-86],[12,-105],[-62,-60],[-112,6],[-77,-125],[81,-65],[160,55],[8,-72],[-150,-31],[-184,42],[-85,-85],[275,-79],[-14,-133],[83,85],[37,-80],[-224,-165],[1,-168],[140,7],[139,-100],[11,-61],[-117,-14],[-181,42],[-35,-170],[143,-43],[2,-74],[-265,-128]],[[33685,51264],[130,119],[87,1],[196,249],[141,25],[61,-76],[294,83],[169,141],[186,79],[40,68],[286,70],[354,-176],[319,-55],[34,-96],[182,-22],[75,-131],[107,36],[137,-67],[170,-12],[98,79],[307,126],[8,80],[139,46],[28,151],[70,-101],[153,206],[133,-50],[136,76],[90,128],[-86,136],[120,35]],[[37849,52412],[28,129],[-142,52],[-66,77],[6,130],[-108,54],[-99,137],[-234,103],[-70,162],[-12,287],[412,555],[-80,84],[12,154],[-45,134],[2479,-39],[623,9],[1055,-27],[1666,-34],[552,-17],[1138,-17]],[[44964,54345],[36,1469],[41,1483],[553,-2],[27,502],[13,737],[98,1489]],[[45732,60023],[-1379,22],[-953,-6],[-835,13],[-1653,46],[-995,17],[-2070,52],[114,182],[233,213],[195,-28],[20,161],[89,89],[142,28],[313,136]],[[38953,60948],[-2392,36],[-843,27],[-1750,31]],[[33968,61042],[-38,-2706],[-70,0],[-19,-1975],[-41,-2977],[-23,-995],[-72,-2],[-20,-1123]],[[21050,20445],[29,2575],[124,-1]],[[21203,23019],[17,1464]],[[21220,24483],[-1652,-26]],[[19568,24457],[-4,-482],[-1664,0],[-1539,8],[-134,-5],[-2400,23],[-1046,2],[-992,-11],[-2236,-13]],[[9553,23979],[5,-982],[-237,-1],[16,-2576]],[[21333,82159],[866,1],[2332,-7],[-17,-2679]],[[31289,82841],[14,721],[21,2344],[9,624],[-1848,15],[-1456,27],[-2,1482]],[[28027,88054],[-1662,10],[-3190,8]],[[21378,88086],[-3,-1495],[-18,-1492],[-1,-995],[-23,-1945]],[[42098,66900],[83,116],[122,58],[94,134],[238,-8],[-20,231],[179,-183],[136,33],[107,146],[290,216],[180,-127],[227,-14],[205,89],[66,154],[251,134],[26,107],[113,171],[158,121],[494,67],[75,113],[317,284],[186,54],[241,149],[204,62],[280,-94],[412,29],[148,-37],[109,-94],[223,163],[363,-26],[263,5],[137,45],[456,2],[144,-172],[78,35],[121,332],[24,226],[128,152],[172,58],[135,127]],[[46067,74413],[-1103,15],[-153,12],[-2063,26]],[[42748,74466],[-1654,28],[-1651,17]],[[39443,74511],[-76,-3873],[-23,-559],[-43,-15],[-29,-746]],[[39272,69318],[-14,-234],[92,-53],[-34,-95],[479,-107],[41,-60],[156,-1],[158,-62],[111,12],[92,84],[92,198],[155,1],[621,-493],[112,-180],[184,-47],[42,-71],[-89,-96],[112,-206],[73,-29],[-62,-235],[229,-286],[-8,-131],[166,-208],[-7,-86],[125,-33]],[[31799,43550],[1677,-16],[-16,-1476],[-10,-1464],[-69,1],[-12,-491],[-18,-1713],[-15,-431],[-47,-3228],[-103,0],[-7,-1480]],[[33179,33252],[1623,-34],[863,-28],[829,-12],[-9,-559]],[[36485,32619],[68,-7],[98,99],[-50,95],[117,2],[38,95],[140,4],[94,-77],[63,81],[252,38],[349,143],[75,-6],[308,-160],[2329,-978],[300,41],[202,158],[80,125],[172,384],[330,392],[121,100],[-171,107],[-12,149],[43,161],[-42,91],[47,221],[53,88],[132,47],[-18,90],[253,90],[16,-39],[190,143],[245,39],[20,128],[176,80],[107,149],[98,-19],[23,133],[78,62],[167,-34],[21,102],[76,-19],[54,82],[40,-78],[100,3],[104,-86],[64,-207],[198,50],[89,-90],[163,39],[-8,78],[122,-51],[-31,115],[110,65],[38,-43],[218,127],[256,-128],[226,-7],[118,51],[-2,123],[-159,-24],[-30,151],[72,-9],[104,219],[-104,44],[19,165],[-96,-29],[100,112],[-182,27],[-99,140],[5,139],[-100,14],[118,147],[10,124],[92,144],[141,36],[38,104],[115,-38],[43,1724],[21,1343]],[[45040,39493],[30,928],[35,1465],[27,1468]],[[45132,43354],[-3071,46],[-277,13],[-1703,6],[-1203,16],[-1222,10],[-4,289],[14,792],[-17,397],[26,1480],[198,1],[49,1731],[68,2098],[3,387],[43,1586],[-66,173],[-71,-86],[-50,119]],[[33685,51264],[-120,-22],[-52,-153],[-101,16],[-28,129],[-355,15],[-265,-36],[-121,-200],[2,-75]],[[32645,50938],[39,-216],[-50,-46],[-121,69],[-68,-78],[-73,96],[-45,-92],[-139,-96],[36,-61],[-119,-39],[-100,35],[-21,-1782],[-55,-2221],[-71,-6],[-59,-2951]],[[32462,83538],[-78,92],[131,76],[114,-3],[15,66],[250,-118],[235,132],[82,138],[263,-13],[165,102],[-16,111],[-86,89],[28,83],[99,-14],[-41,-67],[106,-17],[53,97],[-55,64],[-111,-19],[59,118],[153,-119],[162,104],[-97,104],[197,28],[12,-73],[105,-3],[-1,109],[130,-80],[96,34],[-42,94],[180,-23],[17,115],[71,41],[85,-58],[260,2],[52,142],[126,-28],[63,106],[209,-75],[195,97],[33,97],[329,-16],[71,-75],[-33,168],[153,80],[94,-43],[81,58],[-20,-130],[99,51],[-14,110],[147,136],[76,1],[199,196],[109,-28],[26,297],[122,135],[101,-74],[39,78],[-113,44],[207,258],[171,63],[40,85],[-33,116],[215,112],[364,58]],[[38202,89411],[-2898,39],[-2175,27],[-1668,33]],[[31461,89510],[-1652,22],[-1649,9],[-26,-1486],[-107,-1]],[[14922,31852],[2505,0],[85,-4],[2441,-6],[1668,-15]],[[21621,31827],[36,-2],[18,2487],[3,1943],[14,1477]],[[21692,37732],[-1349,8],[-1019,15],[-958,6],[-1762,-18],[-1679,-5]],[[14925,37738],[1,-1087],[7,-1148],[-9,-2180],[-2,-1471]],[[12253,56936],[15,-1481]],[[12268,55455],[1646,7],[3296,2],[1663,12]],[[18873,55476],[11,2958],[145,-1],[11,2959]],[[19040,61392],[-3315,12],[-3324,-11]],[[12401,61393],[7,-2594],[7,-383],[-167,-1],[5,-1479]],[[53131,12273],[1329,29],[381,-142],[61,16],[17,374],[261,16],[258,171],[197,17],[2173,874],[895,-145],[297,48],[146,499],[-77,108],[56,55],[-118,71],[-225,-30],[-91,88],[-302,-8],[-177,51],[-25,175],[-95,197],[-36,171],[329,313],[320,53],[95,55],[1031,-102],[489,-132],[384,-15],[245,288],[93,25],[90,164],[251,69],[8,221],[-241,504],[102,333],[225,370],[296,403],[77,7],[133,148],[378,700],[57,57],[33,192],[193,299],[199,-176],[267,-69],[222,-120],[435,-79],[138,-72],[-57,-141],[-221,-141],[-160,-385],[76,-304],[-159,-163],[17,-111],[117,-21],[69,-324],[335,-213],[512,79],[78,66],[130,-13],[36,-110],[132,53],[193,-62],[10,-90],[190,-109],[219,-48],[26,160],[775,10],[68,-77],[291,-27],[93,172],[38,237],[115,22],[94,121],[399,60],[-146,411],[20,170],[67,114],[21,252],[224,80],[123,205],[66,52],[65,-155],[137,-5],[149,125],[-125,40],[16,182],[207,32],[55,-63],[274,-89],[289,8],[122,171],[223,131],[55,202],[623,-104],[19,51],[214,90]],[[71139,40246],[-228,166],[-68,119],[-115,-54],[-199,42],[-174,195],[-140,98],[-127,21],[-253,186],[-204,226],[-511,316],[-168,157],[-252,155],[-169,188],[-242,106],[-210,199],[-152,60],[-168,156],[-37,102],[-300,151],[-109,139],[44,165],[206,317],[368,445],[344,346],[142,69],[-64,44],[-185,-76],[-764,-657],[-357,23],[-274,165],[-67,85],[33,159],[-58,160],[-118,4],[-163,-62],[-90,49],[-195,2],[-102,172],[-94,65],[-2,96],[294,43],[91,81],[-57,172],[-144,65],[-163,210],[50,163],[-129,91],[-215,-43],[-182,69],[-194,-155],[-118,135],[-61,8],[-55,-112],[-158,-44],[-21,-118],[-60,70]],[[64795,45180],[-121,-57],[-80,-1649],[-286,-6],[-1386,51],[-261,-4],[-580,19],[-1929,40],[-269,-32],[-285,10],[-1690,100],[-1678,52],[-842,11],[-816,29]],[[54572,43744],[-24,-1469],[-56,-2942]],[[54492,39333],[-52,-1405],[-132,3],[-41,-1468],[-66,-1716],[-6,-628],[-21,-632],[-27,0],[-49,-375],[-29,-1085],[20,-1206],[-24,-751],[-1,-400],[-32,-343],[1,-633],[-20,-1109],[-272,4],[-70,-1453],[-4,-1161],[-13,-286]],[[53654,24689],[-45,-1465],[-94,2],[-27,-487],[-38,-1022],[-97,4],[-53,-1258],[-3,-229],[-61,-1461],[28,-127],[-70,-2685],[12,-96],[-29,-1438],[-24,-807],[-22,-1347]],[[9553,23979],[-5,1964],[1679,8],[7,1473],[1939,17],[4748,-22],[1,-1477],[1657,-10],[-11,-1475]],[[21220,24483],[44,2571],[-2,361],[20,981],[3,490],[331,0],[-4,481],[10,989],[-1,1471]],[[14922,31852],[-1668,-13],[-3901,1],[-77,-5],[-1603,-6],[-847,3],[-2101,-21]],[[4725,31811],[-50,-133],[141,-30],[-132,-23],[88,-119],[-110,44],[-118,-50],[-79,-197],[117,-11],[89,-108],[-122,-79],[98,-26],[134,45],[-195,-119],[132,-126],[-147,-94],[102,-16],[63,-106],[-174,71],[-76,-56],[49,-62],[169,17],[-106,-96],[87,-90],[32,-217],[-75,-170],[-2,-143],[-220,-69],[-69,-73],[46,-61],[-162,-269],[75,-54],[8,-124],[-59,-69],[20,-176],[-52,-87],[38,-95],[-129,-10],[-32,-250],[-102,16],[-71,-225],[2,-111],[-95,-36],[-27,-128],[-109,6],[147,-83],[-171,-249],[51,-223],[-122,-61],[51,-212],[-154,-148],[-116,5],[40,-85],[-80,-10],[7,-91],[-91,13],[99,-119],[-119,-134],[-124,31],[60,-77],[-245,-89],[171,-65],[-27,-182],[-89,-55],[70,-82],[-63,-122],[-97,-22],[-47,-339],[-95,-87],[4,-105],[-206,-43],[26,-130],[-77,-68],[84,-114],[-77,-67],[64,-92],[-61,-131],[100,43],[1,-125],[-84,-48],[79,-65],[-231,-178],[-2,-156],[-194,-69],[-57,-97],[22,-179],[-95,-67],[107,-411],[-17,-85],[-120,-95],[-29,-187],[46,-92],[-115,-70],[47,-145],[-19,-238],[-65,-186],[-145,-94],[-137,-219],[-87,-24],[64,-227],[-129,-94],[100,-88],[-93,-137],[-176,-34],[23,-174],[-149,-342],[145,-24],[-303,-113],[73,-97],[217,-102],[-47,-97],[-138,53],[-80,-51],[-25,-181]],[[12089,46577],[-6,978],[1,1725],[-4,1533],[3,1688],[204,1],[-12,638],[-7,2315]],[[12253,56936],[-1901,-6],[-2242,-15]],[[8110,56915],[-18,-85],[159,-417],[71,-68],[55,-160],[-15,-123],[50,-202],[-60,-359],[-102,-166],[88,-31],[-93,-55],[-16,-213],[-155,-323],[56,-141],[-30,-146],[-64,-52],[48,-103],[-171,34],[86,-109],[-55,-146],[73,-73],[18,-236],[-95,-4],[-61,-192],[-43,-274],[13,-122],[175,-77],[-134,-106],[-60,-140],[58,-248],[-64,-69],[63,-72],[-78,-40],[61,-76],[-113,-25],[109,-89],[-80,-75],[87,-249],[-53,-34],[1,-197],[-257,-175],[58,-77],[-164,-63],[-9,-80],[-214,56],[-37,-102],[60,-93],[-152,-62],[-142,-147],[-120,-295],[35,-62],[-123,-210],[-77,37],[11,-152],[-141,32],[-55,-56],[131,-11],[-19,-94],[-129,78],[33,-212],[-85,-33],[53,-78],[-164,-16],[46,-70],[-114,-137],[89,-1],[-31,-108],[65,-68],[-92,-37],[76,-72],[-133,-33],[118,-46],[-169,-19],[-43,-111],[-104,12],[73,-80],[-10,-249],[-116,-51],[101,-121],[-64,-214],[19,-100],[-87,-165],[93,16],[-43,-147],[-116,-14],[70,-453],[-98,-10],[77,-76],[-118,23],[61,-148],[-23,-91],[-128,-21],[98,-88],[-200,-13],[-25,-140],[-78,-72],[41,-226],[-153,33],[115,-132],[-167,25],[81,-82]],[[10636,6498],[-8,1810],[2,1469],[-10,1486],[223,0],[-14,1449],[-13,221],[9,1244]],[[871,14111],[11,-171],[86,50],[190,0],[-64,-102],[-252,0],[-113,-57],[48,-79],[248,-39],[28,-156],[-135,-38],[22,-54],[129,23],[71,-45],[19,-120],[-141,-53],[114,-74],[122,-159],[-177,-10],[43,-105],[190,22],[-62,-148],[146,70],[47,-60],[-135,-129],[95,-76],[127,59],[51,-143],[-76,-95],[102,-54],[110,-190],[-120,-70],[118,-137],[-23,-166],[103,-13],[17,-71],[-220,-94],[-135,-206],[135,-65],[-114,-61],[-93,-166],[-133,-84],[88,-137],[-152,-57],[67,-74],[-15,-140],[-140,-4],[-70,-120],[115,-136],[-145,-193],[115,-37],[-114,-60],[7,-123],[-180,-35],[-34,-55],[135,-16],[-22,-85],[-138,61],[-39,-60],[261,-88],[1,-75],[-196,-22],[-207,-63],[138,-73],[25,-78],[-84,-146],[137,-81],[-41,-123],[51,-79],[-75,-216],[-135,-9],[128,-152],[8,-74],[-125,6],[-116,-63],[16,-109],[-54,-85],[153,-45],[-57,-72],[-170,-67],[-63,-94],[22,-143],[-109,-92],[72,-160],[-105,-20],[-53,-96],[6,-122],[-95,-35],[61,-275],[-102,-24],[-6,-291],[152,-171],[-95,-58],[74,-73],[1299,18],[2493,24],[0,8],[3337,25],[3362,17]],[[14925,37738],[-1674,9]],[[4788,37718],[45,-103],[231,-140],[-73,-28],[-24,-184],[46,-141],[-170,9],[129,-66],[-156,-125],[-76,22],[137,-131],[44,-142],[-88,-85],[50,-45],[-120,-73],[139,-47],[-139,-92],[71,-61],[111,13],[-101,-140],[47,-58],[-69,-174],[-87,-30],[129,-53],[-145,1],[127,-138],[-138,-46],[96,-88],[-46,-272],[175,-209],[-65,-92],[-93,35],[-53,-121],[149,-52],[-17,-94],[108,-61],[-97,-40],[-56,63],[-73,-54],[148,-43],[56,-104],[-130,-40],[-87,-144],[47,-88],[-78,-39],[-2,-157],[-86,-2],[37,-108],[136,-80],[-59,-91],[131,10],[-16,-174],[-123,-19],[128,-100],[-167,-130],[134,-62],[-212,7],[-40,-128],[-118,-40],[190,-64],[-116,-69],[148,-57],[-115,-100],[85,-43],[-86,-269],[104,-64],[-79,-221],[110,-125],[-206,15],[66,-78],[96,9],[39,-71],[-155,-72],[209,-124]],[[21692,37732],[904,-9],[1081,5],[3026,-44]],[[26703,37684],[-6,985],[23,1353],[-3,619],[106,-1],[16,1742],[3,1203]],[[26842,43585],[6,1478]],[[26848,45063],[-836,14],[-277,18],[-998,5],[-1478,16],[-701,-24],[-715,30],[-1657,14],[-1671,-11],[-1667,-1],[-1507,-20],[-1564,-8],[-278,5]],[[46211,80178],[-17,-567],[-1643,35],[-16,-745],[-1658,24]],[[42877,78925],[-26,-1392],[-36,-1586],[-26,0],[-27,-740],[-14,-741]],[[21203,23019],[4579,-15],[-227,249],[-326,765],[-59,286],[-4,309],[108,357],[137,211],[170,136],[354,130],[330,46],[24,3370],[121,0],[19,1475],[44,2198],[3,738]],[[26476,33274],[21,1479],[171,0],[35,2931]],[[31461,89510],[22,991],[44,3456]],[[31527,93957],[-1444,20],[-966,6],[-2018,22],[-1311,2],[-2436,17]],[[23352,94024],[-137,1]],[[46573,93722],[1646,-38]],[[48219,93684],[6,127],[88,3358],[69,2480]],[[48382,99649],[-2019,44],[-2445,47],[-1692,19],[-2148,36]],[[40078,99795],[-86,-4207],[-26,-1743]],[[35908,11397],[177,-171],[350,-22],[261,89],[332,46],[183,-21],[254,-101],[343,78],[97,89],[178,57],[125,215],[-38,331],[135,174],[259,62],[317,-30],[408,41],[134,38],[607,16],[129,-31],[112,35],[326,-47],[20,40],[270,0],[177,40],[288,-45],[392,88],[169,4],[116,55],[352,36],[197,-62],[317,59],[551,13],[126,72],[87,200],[70,65],[59,230],[141,251],[39,168],[-79,333],[16,139],[-86,210],[81,87],[231,143],[534,4],[141,-40],[420,-21],[187,51],[257,-31],[231,4],[144,-29],[161,-220],[75,-16],[108,116],[100,36],[205,-125],[207,34],[208,-45],[191,-1],[404,-112],[194,-113],[416,-85],[84,-84],[47,-192],[-133,-426],[20,-76],[330,-35],[163,-138],[269,-142],[70,90],[356,-28],[111,-151],[87,36],[93,-256],[1179,-302],[608,-11],[307,230],[80,83],[1146,-103]],[[53654,24689],[-840,5],[-3420,62],[-727,7],[-1391,-21],[-1969,57],[-2,-23],[-659,10],[18,888],[-2536,33],[-2348,59],[-1766,37],[-1685,30]],[[36329,25833],[-11,-1230],[-34,-1712],[-76,1],[-37,-2142],[7,-173],[-65,-2067],[-42,-1487],[-38,1]],[[9649,80635],[1838,18],[1808,-5],[1243,14]],[[14538,80662],[-5,1482],[176,6],[11,2189],[-1,2246],[8,1493]],[[14727,88078],[-2280,-19],[-2818,0],[-34,4]],[[9595,88063],[10,-1470],[27,-3037],[-3,-216],[20,-2705]],[[31595,93956],[2274,-27],[4418,-59]],[[40078,99795],[-3082,47],[-5321,62]],[[31675,99904],[-52,-3725],[-28,-2223]],[[45113,52868],[1474,-58],[2012,-85],[1374,-20],[48,1439],[-16,133]],[[50005,54277],[61,2441],[19,495],[-1142,22],[58,1955],[39,777],[67,1050],[18,428]],[[49125,61445],[38,536],[19,982],[72,1471]],[[49254,64434],[-959,18],[-849,6],[-1534,35]],[[45912,64493],[-60,-1650],[-57,-1340],[-8,-512],[-55,-968]],[[44964,54345],[-46,-1472],[195,-5]],[[61431,93327],[151,-4],[-48,-1195],[-29,-896],[-76,-1921],[-85,-1921]],[[61344,87390],[1753,-45]],[[63097,87345],[3179,-91],[64,1475],[1019,-33],[1924,-55],[344,-16]],[[69627,88625],[82,1481],[25,679],[43,798],[59,1485]],[[69836,93068],[-1782,64],[-1510,36],[-1799,57],[8,243]],[[64753,93468],[-3311,110],[-11,-251]],[[9557,94003],[909,11],[2011,14],[1773,0],[664,-4]],[[15083,94024],[-6,2121],[-4,129],[-10,2225],[9,1091],[-4,406]],[[15068,99996],[-5543,-16],[14,-2990],[18,-2987]],[[27014,50988],[1936,-11],[1399,-17],[971,-3],[1325,-19]],[[33968,61042],[-682,13],[-2027,10],[-609,13],[-693,4],[-2629,38]],[[27328,61120],[-23,-1482],[7,-1231],[-99,-1],[-21,-1481],[-4,-1479]],[[27188,55446],[-24,-1734],[-5,-1254],[-112,0],[-33,-1470]],[[67133,82773],[137,146],[241,110],[729,167],[522,68],[190,133],[329,75],[121,64],[233,4],[113,43],[220,208],[263,119],[148,22],[300,168],[235,47],[152,105],[264,305],[221,119],[184,372],[-133,250],[61,179],[202,75],[146,142],[4,173],[99,113],[25,165],[-60,194],[51,150],[139,161],[83,271],[236,120]],[[72588,87041],[-3025,115],[64,1469]],[[63097,87345],[-119,-2966],[1642,-50],[-58,-1487],[2571,-69]],[[45040,39493],[1602,-9],[1077,-33],[1675,-21],[1694,-38],[388,11],[1239,-1],[1777,-69]],[[54572,43744],[13,1591],[74,1350],[105,-2],[-6,242],[52,1225],[56,1488]],[[54866,49638],[67,1482],[40,1347],[61,1610]],[[55034,54077],[-1098,28],[-1972,31],[-272,16],[-1387,110],[-300,15]],[[45113,52868],[-38,-93],[-71,27],[-89,-101],[-50,-2058],[-14,-734],[-65,-1475],[6,-198],[-31,-1160],[441,-101],[-23,-681],[-36,-2025],[-11,-915]],[[20911,14268],[260,3],[1959,-30],[1116,-12]],[[36329,25833],[21,1469],[38,1469],[13,0],[37,1324],[28,125],[3,740],[16,1659]],[[33179,33252],[-558,15],[-561,-8],[-432,17],[-1808,3],[-282,-9],[-635,8],[-2427,-4]],[[74641,92886],[3026,-126],[1485,-59],[1634,-75]],[[80786,92626],[97,155],[101,407],[118,224],[35,139],[269,288],[-127,516],[18,194],[-43,175],[-121,238],[23,242],[-50,329],[34,370],[116,120],[19,161],[-63,189],[8,205],[156,197],[278,222],[108,132],[3,291],[-137,275],[17,151],[97,122],[61,151],[227,187],[6,204],[-610,19],[-1876,84],[-615,34],[-681,25],[-2220,96],[-1091,40]],[[74943,98808],[-25,-395],[-131,-2563],[-45,-984],[-101,-1980]],[[49125,61445],[1673,21],[910,-26],[1846,-40],[556,-17]],[[54110,61383],[20,491],[77,2447],[1613,-32],[26,880],[30,603],[63,998]],[[55939,66770],[-857,7],[-136,-14],[-659,20],[-279,-2],[-977,32],[-1489,42],[-1255,30],[-953,2]],[[49334,66887],[-36,-978],[-44,-1475]],[[55034,54077],[34,1476],[55,1533],[-1172,36],[51,1299],[108,2962]],[[14538,80662],[821,6],[2222,-12],[1946,7],[1674,-1],[2,1493],[130,4]],[[14930,88082],[-203,-4]],[[42877,78925],[-1653,32],[-1661,20],[22,1495],[-1108,11],[-2204,46],[-30,-1490]],[[36131,76049],[-19,-1492],[1181,-3],[837,-13],[1313,-30]],[[32485,68693],[1658,-11],[1412,-28],[1501,-22],[545,-18],[17,749],[249,5],[985,-30],[420,-20]],[[32660,76097],[-29,-2973],[-20,-1487],[-30,-1461],[-78,1],[-18,-1484]],[[56469,93474],[49,-2]],[[56518,93472],[2314,-71],[2599,-74]],[[64753,93468],[53,1260],[54,1471],[134,2977]],[[64994,99176],[-2773,96],[-1424,43],[-529,25],[-3585,103]],[[56683,99443],[-34,-886],[-96,-2806],[-84,-2277]],[[9557,94003],[10,-2199],[28,-3741]],[[19040,61392],[3310,6],[1366,-23],[572,13],[2069,-11],[974,-10]],[[27331,61367],[27,2043],[1,919],[113,-1],[16,1531],[10,1412]],[[27498,67271],[-1663,10]],[[25835,67281],[-1649,11],[-1653,19],[-1665,-2],[-1661,6]],[[19207,67315],[-14,-2952],[-142,1],[-13,-2099],[2,-873]],[[56247,75655],[-204,-116],[-104,-121],[-119,-242],[-1063,26],[-99,250],[-229,216],[-201,85],[-130,1]],[[53359,73258],[-61,-1516],[2802,-64]],[[52890,81670],[37,1229],[2074,-41],[1233,-44]],[[56234,82814],[142,4702]],[[56376,87516],[-65,2]],[[56311,87518],[-3298,91],[-1646,43]],[[51367,87652],[-1627,42]],[[49740,87694],[-57,-1983],[-23,-994],[-82,-2961]],[[10636,6498],[2506,7],[5640,6],[3596,-2],[2097,-9]],[[40672,64603],[1762,-34],[2122,-58],[1356,-18]],[[49334,66887],[19,497],[27,1518],[11,869]],[[42098,66900],[-71,-210],[-176,49],[-56,-100],[-132,11],[-31,-152],[-199,-58],[-79,-71],[14,-203],[-205,-208],[-146,-58],[-220,-177],[-20,-259],[45,-136],[-153,-215],[47,-136],[10,-280],[-54,-94]],[[56311,87518],[20,490],[68,1985],[76,1988],[34,987],[9,504]],[[56469,93474],[-2477,70],[-2443,63]],[[51549,93607],[-64,-2128],[-22,-848],[-96,-2979]],[[14228,67324],[1654,-5],[3325,-4]],[[25835,67281],[27,2964],[115,0],[15,1472]],[[12401,61393],[-4,1484],[9,1486]],[[4582,64313],[-296,-340],[187,-572],[48,-97],[548,-389],[530,-322],[143,-191],[528,-316],[322,-141],[197,-108],[275,-245],[140,-221],[44,-175],[182,-302],[172,-110],[214,-294],[129,-78],[100,-160],[72,-293],[47,-742],[35,-24],[8,-252],[53,-111],[-77,-45],[83,-128],[6,-266],[33,-178],[-52,-199],[-67,-107],[-39,-659],[-37,-333]],[[26842,43585],[1653,-29],[1662,-7],[467,-6],[453,12],[722,-5]],[[27014,50988],[1,-313],[-44,-4123],[-104,1],[-22,-1241],[3,-249]],[[72588,87041],[194,132],[219,103],[174,235],[292,158],[310,104],[322,205],[291,21],[162,63],[124,138],[57,282],[172,84],[190,13],[208,170],[114,214],[214,187],[90,-13],[147,122],[289,133],[145,207],[213,121],[326,22],[167,45],[313,1],[238,32],[173,103],[198,67],[169,-30],[391,120],[153,124],[90,189],[168,150],[98,159],[287,153],[308,319],[28,141],[89,156],[138,84],[145,239],[250,146],[80,111],[73,244],[208,200],[181,131]],[[74641,92886],[-899,32],[-1094,49],[-2812,101]],[[64795,45180],[36,651],[85,2054],[53,1474]],[[64969,49359],[-2725,78],[-3969,120],[-1187,22],[-2222,59]],[[18873,55476],[1126,0],[2665,-25],[1203,-5],[1154,5],[2167,-5]],[[27328,61120],[3,247]],[[74943,98808],[-3040,122],[-3170,112],[-1387,54],[-2352,80]],[[56234,82814],[-24,-746],[491,-19],[249,-58],[162,66],[224,-4],[32,128],[110,-98],[116,16],[254,-112],[-14,-439],[1724,-46],[-56,-1481],[825,-21],[-39,-858],[-17,-579]],[[60271,78563],[436,327],[514,503],[124,87],[329,144],[148,167],[34,166],[-14,243],[96,53],[178,-11],[155,100],[82,101],[100,-92],[106,23],[283,374],[6,207],[130,25],[176,-113],[121,-32],[134,79],[207,66],[173,-44],[357,98],[195,-23],[130,-55],[222,86],[357,33],[281,-35],[285,26],[257,98],[213,213],[52,156],[123,206],[15,276],[164,248],[203,195],[202,138],[187,90],[101,87]],[[61344,87390],[-2098,43],[-2870,83]],[[48219,93684],[1670,-36],[1660,-41]],[[56683,99443],[-2489,67],[-594,19],[-3125,75],[-2093,45]],[[31527,93957],[68,-1]],[[31675,99904],[-1939,21],[-274,-3],[-1949,24],[-1246,-4],[-85,13],[-2538,19],[-281,-5]],[[23363,99969],[-9,-2097],[9,-868],[-4,-1239],[9,-253],[-16,-1488]],[[64969,49359],[70,1620],[94,2410],[54,1126],[23,671],[-168,40],[-277,115],[-95,119],[-96,283],[7,246],[-70,86],[-4,113],[-104,64],[-198,-6],[-270,-82],[-245,-123],[-134,13],[-195,100],[-85,89],[-22,121],[-91,151],[-18,129],[-118,90],[-19,198],[-108,60],[-245,-36],[-157,-71],[-263,-63],[-205,116],[-154,172],[-18,279],[-304,70],[-199,114],[-164,22],[-154,112],[-198,42],[-143,-15],[17,153],[-227,9],[-260,219],[-2,97],[-292,178],[-116,30],[-172,194],[-162,273],[-56,351],[-80,107],[-211,136],[-49,114],[114,270],[-46,171],[-133,106],[-93,219],[-55,315],[-233,217],[-91,134],[-250,185],[-263,93]],[[58036,61305],[-77,-20],[-1418,37],[-1462,29],[-969,32]],[[44313,81876],[-24,81],[107,-4],[44,146],[182,56],[42,129],[-20,248],[-105,228],[-116,66],[-35,237],[-52,44],[-119,-51],[-101,76],[143,113],[-171,113]],[[44088,83358],[-1092,24],[-2222,33],[-1073,24],[-3436,55],[-966,22],[-699,7]],[[40672,64603],[-155,-122],[-80,-162],[-66,-233],[-287,-185],[-163,-316],[-18,-459],[82,-102],[-6,-277],[157,-105],[7,-96],[-165,66],[-70,-26],[-102,-389],[-136,-91],[-65,-148],[135,-110],[-12,-78],[-299,-65],[-303,-200],[-97,-207],[22,-144],[-110,-78],[12,-128]],[[23363,99969],[-835,18],[-3132,10],[-1668,2],[-2660,-3]],[[58036,61305],[-20,75],[-160,41],[-86,82],[-23,304],[-43,185],[-31,400],[-44,106],[-60,350],[29,328],[61,160],[-42,263],[45,85],[3,245],[175,129],[331,9],[315,85],[291,-41],[209,-92],[209,10],[185,155],[155,72],[270,195],[-16,264],[25,190],[206,184],[137,171],[154,281],[161,198],[377,156],[91,217],[-34,385],[52,99],[-41,253],[-180,94],[-165,230],[-25,127],[-227,164],[-95,171],[80,293],[-138,261],[-232,212],[-120,155],[-111,82]],[[56010,68727],[-28,-770],[-5,-560],[-38,-627]],[[49740,87694],[-3328,79]],[[43051,87092],[-141,-20],[91,-132],[74,37],[-4,-105],[-86,-84],[-114,27],[37,-98],[99,-59],[41,-203],[175,-38],[89,-287],[240,-89],[98,-115],[86,-6],[118,-226],[-28,-72],[122,-116],[-25,-132],[108,-2],[61,-102],[-153,-169],[-143,-32],[-94,-106],[-22,-127],[85,-52],[-23,-97],[-82,-36],[134,-38],[-16,-98],[-123,-55],[168,-4],[-3,-239],[-48,-48],[179,-50],[82,-229],[82,-339],[-78,-82],[51,-111]],[[59291,78043],[205,137],[302,125],[127,95],[273,105],[73,58]],[[9649,80635],[15,-1486],[4,-1490]],[[27498,67271],[1656,-13],[1648,-28],[1663,-16],[20,1479]]]}
